{
  "swagger": "2.0",
  "info": {
    "title": "CodeCollab API",
    "description": "API docs for CodeCollab app",
    "version": "1.0.0"
  },
  "host": "localhost:3000",
  "basePath": "/",
  "schemes": [
    "http"
  ],
  "paths": {
    "/": {
      "get": {
        "description": "",
        "responses": {
          "200": {
            "description": "OK"
          }
        }
      }
    },
    "/api/v1/auth/register": {
      "post": {
        "description": "",
        "responses": {
          "default": {
            "description": ""
          }
        }
      }
    },
    "/api/v1/auth/login": {
      "post": {
        "description": "",
        "responses": {
          "default": {
            "description": ""
          }
        }
      }
    },
    "/api/v1/auth/verify/user": {
      "post": {
        "description": "",
        "responses": {
          "default": {
            "description": ""
          }
        }
      }
    },
    "/api/v1/auth/verify/code": {
      "post": {
        "description": "",
        "responses": {
          "default": {
            "description": ""
          }
        }
      }
    },
    "/api/v1/auth/forget-password": {
      "post": {
        "description": "",
        "responses": {
          "default": {
            "description": ""
          }
        }
      }
    },
    "/api/v1/auth/verify/password-reset-code": {
      "post": {
        "description": "",
        "responses": {
          "default": {
            "description": ""
          }
        }
      }
    },
    "/api/v1/auth/reset-password": {
      "post": {
        "description": "",
        "responses": {
          "default": {
            "description": ""
          }
        }
      }
    },
    "/api/v1/user/{@handle}": {
      "get": {
        "description": "",
        "parameters": [
          {
            "name": "@handle",
            "in": "path",
            "required": true,
            "type": "string"
          }
        ],
        "responses": {
          "default": {
            "description": ""
          }
        }
      }
    },
    "/api/v1/user/profile": {
      "get": {
        "description": "",
        "responses": {
          "default": {
            "description": ""
          }
        }
      }
    },
    "/api/v1/user/edit/status": {
      "put": {
        "description": "",
        "responses": {
          "default": {
            "description": ""
          }
        }
      }
    },
    "/api/v1/user/edit/name": {
      "put": {
        "description": "",
        "responses": {
          "default": {
            "description": ""
          }
        }
      }
    },
    "/api/v1/user/block": {
      "put": {
        "description": "",
        "responses": {
          "default": {
            "description": ""
          }
        }
      }
    },
    "/api/v1/user/unblock": {
      "put": {
        "description": "",
        "responses": {
          "default": {
            "description": ""
          }
        }
      }
    },
    "/api/v1/group/": {
      "post": {
        "description": "",
        "responses": {
          "default": {
            "description": ""
          }
        }
      }
    },
    "/api/v1/group/public": {
      "get": {
        "description": "",
        "responses": {
          "default": {
            "description": ""
          }
        }
      }
    },
    "/api/v1/group/my": {
      "get": {
        "description": "",
        "responses": {
          "default": {
            "description": ""
          }
        }
      }
    },
    "/api/v1/group/{groupId}": {
      "get": {
        "description": "",
        "parameters": [
          {
            "name": "groupId",
            "in": "path",
            "required": true,
            "type": "string"
          }
        ],
        "responses": {
          "default": {
            "description": ""
          }
        }
      },
      "put": {
        "description": "",
        "parameters": [
          {
            "name": "groupId",
            "in": "path",
            "required": true,
            "type": "string"
          }
        ],
        "responses": {
          "default": {
            "description": ""
          }
        }
      },
      "delete": {
        "description": "",
        "parameters": [
          {
            "name": "groupId",
            "in": "path",
            "required": true,
            "type": "string"
          }
        ],
        "responses": {
          "default": {
            "description": ""
          }
        }
      }
    },
    "/api/v1/group/{groupId}/invite": {
      "post": {
        "description": "",
        "parameters": [
          {
            "name": "groupId",
            "in": "path",
            "required": true,
            "type": "string"
          }
        ],
        "responses": {
          "default": {
            "description": ""
          }
        }
      }
    },
    "/api/v1/group/{groupId}/accept-invitation": {
      "post": {
        "description": "",
        "parameters": [
          {
            "name": "groupId",
            "in": "path",
            "required": true,
            "type": "string"
          }
        ],
        "responses": {
          "default": {
            "description": ""
          }
        }
      }
    },
    "/api/v1/group/{groupId}/reject-invitation": {
      "post": {
        "description": "",
        "parameters": [
          {
            "name": "groupId",
            "in": "path",
            "required": true,
            "type": "string"
          }
        ],
        "responses": {
          "default": {
            "description": ""
          }
        }
      }
    },
    "/api/v1/group/{groupId}/leave": {
      "post": {
        "description": "",
        "parameters": [
          {
            "name": "groupId",
            "in": "path",
            "required": true,
            "type": "string"
          }
        ],
        "responses": {
          "default": {
            "description": ""
          }
        }
      }
    },
    "/api/v1/group/{groupId}/members": {
      "get": {
        "description": "",
        "parameters": [
          {
            "name": "groupId",
            "in": "path",
            "required": true,
            "type": "string"
          }
        ],
        "responses": {
          "default": {
            "description": ""
          }
        }
      }
    },
    "/api/v1/group/{groupId}/upload-image": {
      "post": {
        "description": "",
        "parameters": [
          {
            "name": "groupId",
            "in": "path",
            "required": true,
            "type": "string"
          }
        ],
        "responses": {
          "default": {
            "description": ""
          }
        }
      }
    },
    "/api/v1/group/{groupId}/members/{userId}": {
      "post": {
        "description": "",
        "parameters": [
          {
            "name": "groupId",
            "in": "path",
            "required": true,
            "type": "string"
          },
          {
            "name": "userId",
            "in": "path",
            "required": true,
            "type": "string"
          }
        ],
        "responses": {
          "default": {
            "description": ""
          }
        }
      }
    },
    "/api/v1/group/{groupId}/promote/{userId}": {
      "put": {
        "description": "",
        "parameters": [
          {
            "name": "groupId",
            "in": "path",
            "required": true,
            "type": "string"
          },
          {
            "name": "userId",
            "in": "path",
            "required": true,
            "type": "string"
          }
        ],
        "responses": {
          "default": {
            "description": ""
          }
        }
      }
    },
    "/api/v1/group/{groupId}/messages": {
      "get": {
        "description": "",
        "parameters": [
          {
            "name": "groupId",
            "in": "path",
            "required": true,
            "type": "string"
          }
        ],
        "responses": {
          "default": {
            "description": ""
          }
        }
      }
    },
    "/api/v1/group/{groupId}/message": {
      "post": {
        "description": "",
        "parameters": [
          {
            "name": "groupId",
            "in": "path",
            "required": true,
            "type": "string"
          }
        ],
        "responses": {
          "default": {
            "description": ""
          }
        }
      }
    },
    "/api/v1/group/{groupId}/message/{messageId}": {
      "delete": {
        "description": "",
        "parameters": [
          {
            "name": "groupId",
            "in": "path",
            "required": true,
            "type": "string"
          },
          {
            "name": "messageId",
            "in": "path",
            "required": true,
            "type": "string"
          }
        ],
        "responses": {
          "default": {
            "description": ""
          }
        }
      }
    },
    "/api/v1/group/{groupId}/voice": {
      "post": {
        "description": "",
        "parameters": [
          {
            "name": "groupId",
            "in": "path",
            "required": true,
            "type": "string"
          }
        ],
        "responses": {
          "default": {
            "description": ""
          }
        }
      }
    },
    "/api/v1/group/{groupId}/image": {
      "post": {
        "description": "",
        "parameters": [
          {
            "name": "groupId",
            "in": "path",
            "required": true,
            "type": "string"
          }
        ],
        "responses": {
          "default": {
            "description": ""
          }
        }
      }
    },
    "/api/v1/call/{groupId}/start": {
      "post": {
        "description": "",
        "parameters": [
          {
            "name": "groupId",
            "in": "path",
            "required": true,
            "type": "string"
          }
        ],
        "responses": {
          "default": {
            "description": ""
          }
        }
      }
    },
    "/api/v1/call/{groupId}/end": {
      "post": {
        "description": "",
        "parameters": [
          {
            "name": "groupId",
            "in": "path",
            "required": true,
            "type": "string"
          }
        ],
        "responses": {
          "default": {
            "description": ""
          }
        }
      }
    },
    "/api/v1/call/{groupId}/join": {
      "post": {
        "description": "",
        "parameters": [
          {
            "name": "groupId",
            "in": "path",
            "required": true,
            "type": "string"
          }
        ],
        "responses": {
          "default": {
            "description": ""
          }
        }
      }
    },
    "/api/v1/call/{groupId}/leave": {
      "post": {
        "description": "",
        "parameters": [
          {
            "name": "groupId",
            "in": "path",
            "required": true,
            "type": "string"
          }
        ],
        "responses": {
          "default": {
            "description": ""
          }
        }
      }
    },
    "/api/v1/call/{groupId}/duration": {
      "get": {
        "description": "",
        "parameters": [
          {
            "name": "groupId",
            "in": "path",
            "required": true,
            "type": "string"
          }
        ],
        "responses": {
          "default": {
            "description": ""
          }
        }
      }
    },
    "/api/v1/call/{groupId}/members": {
      "get": {
        "description": "",
        "parameters": [
          {
            "name": "groupId",
            "in": "path",
            "required": true,
            "type": "string"
          }
        ],
        "responses": {
          "default": {
            "description": ""
          }
        }
      }
    },
    "/api/v1/call/{groupId}/calls": {
      "get": {
        "description": "",
        "parameters": [
          {
            "name": "groupId",
            "in": "path",
            "required": true,
            "type": "string"
          }
        ],
        "responses": {
          "default": {
            "description": ""
          }
        }
      }
    },
    "/api/v1/complier/{groupId}/code": {
      "get": {
        "description": "",
        "parameters": [
          {
            "name": "groupId",
            "in": "path",
            "required": true,
            "type": "string"
          }
        ],
        "responses": {
          "default": {
            "description": ""
          }
        }
      },
      "post": {
        "description": "",
        "parameters": [
          {
            "name": "groupId",
            "in": "path",
            "required": true,
            "type": "string"
          }
        ],
        "responses": {
          "default": {
            "description": ""
          }
        }
      }
    },
    "/api/v1/complier/{groupId}/run": {
      "post": {
        "description": "",
        "parameters": [
          {
            "name": "groupId",
            "in": "path",
            "required": true,
            "type": "string"
          }
        ],
        "responses": {
          "default": {
            "description": ""
          }
        }
      }
    },
    "/api/v1/friend/requests/{@handle}/send": {
      "post": {
        "description": "",
        "parameters": [
          {
            "name": "@handle",
            "in": "path",
            "required": true,
            "type": "string"
          }
        ],
        "responses": {
          "default": {
            "description": ""
          }
        }
      }
    },
    "/api/v1/friend/requests/{@handle}/accept": {
      "post": {
        "description": "",
        "parameters": [
          {
            "name": "@handle",
            "in": "path",
            "required": true,
            "type": "string"
          }
        ],
        "responses": {
          "default": {
            "description": ""
          }
        }
      }
    },
    "/api/v1/friend/requests/{@handle}/reject": {
      "post": {
        "description": "",
        "parameters": [
          {
            "name": "@handle",
            "in": "path",
            "required": true,
            "type": "string"
          }
        ],
        "responses": {
          "default": {
            "description": ""
          }
        }
      }
    },
    "/api/v1/friend/requests/{@handle}/unfriend": {
      "post": {
        "description": "",
        "parameters": [
          {
            "name": "@handle",
            "in": "path",
            "required": true,
            "type": "string"
          }
        ],
        "responses": {
          "default": {
            "description": ""
          }
        }
      }
    },
    "/api/v1/friend/requests/{@handle}/block": {
      "post": {
        "description": "",
        "parameters": [
          {
            "name": "@handle",
            "in": "path",
            "required": true,
            "type": "string"
          }
        ],
        "responses": {
          "default": {
            "description": ""
          }
        }
      }
    },
    "/api/v1/friend/requests/{@handle}/unblock": {
      "post": {
        "description": "",
        "parameters": [
          {
            "name": "@handle",
            "in": "path",
            "required": true,
            "type": "string"
          }
        ],
        "responses": {
          "default": {
            "description": ""
          }
        }
      }
    },
    "/api/v1/friend/": {
      "get": {
        "description": "",
        "responses": {
          "default": {
            "description": ""
          }
        }
      }
    },
    "/api/v1/friend/requests": {
      "get": {
        "description": "",
        "responses": {
          "default": {
            "description": ""
          }
        }
      }
    },
    "/api/v1/friend/blocked": {
      "get": {
        "description": "",
        "responses": {
          "default": {
            "description": ""
          }
        }
      }
    },
    "/api/v1/friend/message/{@handle}": {
      "post": {
        "description": "",
        "parameters": [
          {
            "name": "@handle",
            "in": "path",
            "required": true,
            "type": "string"
          }
        ],
        "responses": {
          "default": {
            "description": ""
          }
        }
      }
    },
    "/api/v1/friend/message/{messageId}/{@handle}": {
      "put": {
        "description": "",
        "parameters": [
          {
            "name": "messageId",
            "in": "path",
            "required": true,
            "type": "string"
          },
          {
            "name": "@handle",
            "in": "path",
            "required": true,
            "type": "string"
          }
        ],
        "responses": {
          "default": {
            "description": ""
          }
        }
      },
      "delete": {
        "description": "",
        "parameters": [
          {
            "name": "messageId",
            "in": "path",
            "required": true,
            "type": "string"
          },
          {
            "name": "@handle",
            "in": "path",
            "required": true,
            "type": "string"
          }
        ],
        "responses": {
          "default": {
            "description": ""
          }
        }
      }
    },
    "/api/v1/friend/messages/{@handle}": {
      "get": {
        "description": "",
        "parameters": [
          {
            "name": "@handle",
            "in": "path",
            "required": true,
            "type": "string"
          }
        ],
        "responses": {
          "default": {
            "description": ""
          }
        }
      }
    },
    "/api/v1/friend/messages/{@handle}/send-image": {
      "post": {
        "description": "",
        "parameters": [
          {
            "name": "@handle",
            "in": "path",
            "required": true,
            "type": "string"
          }
        ],
        "responses": {
          "default": {
            "description": ""
          }
        }
      }
    }
  }
}